tiny_http_server/__init__.py
tiny_http_server/server.py
tiny_http_server-0.5.dist-info/LICENSE
tiny_http_server-0.5.dist-info/METADATA
tiny_http_server-0.5.dist-info/WHEEL
tiny_http_server-0.5.dist-info/entry_points.txt
tiny_http_server-0.5.dist-info/top_level.txt
tiny_http_server-0.5.dist-info/RECORD
