Metadata-Version: 2.1
Name: tiny-http-server
Version: 0.5
Summary: Simple ad-hoc static web page server with basic auth and https support
Home-page: https://github.com/johann-petrak/python-tiny-http-server
Author: Johann Petrak
Author-email: johann.petrak@gmail.com
License: MIT License
Keywords: tools,http,https,server
Platform: any
Classifier: Development Status :: 4 - Beta
Classifier: License :: OSI Approved :: MIT License
Classifier: Programming Language :: Python :: 3.7
Classifier: Programming Language :: Python :: 3.8
Classifier: Programming Language :: Python :: 3.9
Classifier: Programming Language :: Python :: 3.10
Classifier: Programming Language :: Python :: 3
Classifier: Programming Language :: Python :: 3 :: Only
Classifier: Intended Audience :: Developers
Requires-Python: >=3.7
